vb2py/__init__.py
vb2py/basesource.py
vb2py/config.py
vb2py/controls.py
vb2py/conversionserver.py
vb2py/convertasp.py
vb2py/converter.py
vb2py/db_driven_tester.py
vb2py/extensions.py
vb2py/logger.py
vb2py/parserclasses.py
vb2py/projectconverter.py
vb2py/utils.py
vb2py/vb2py.ini
vb2py/vbclasses.py
vb2py/vbconstants.py
vb2py/vbdebug.py
vb2py/vbfunctions.py
vb2py/vbparser.py
vb2py/vbtreeview.py
vb2py/PythonCard/EXIF.py
vb2py/PythonCard/STCStyleEditor.py
vb2py/PythonCard/__init__.py
vb2py/PythonCard/__version__.py
vb2py/PythonCard/about.py
vb2py/PythonCard/clipboard.py
vb2py/PythonCard/component.py
vb2py/PythonCard/configuration.py
vb2py/PythonCard/debug.py
vb2py/PythonCard/dialog.py
vb2py/PythonCard/documentation.py
vb2py/PythonCard/error.py
vb2py/PythonCard/event.py
vb2py/PythonCard/flatfileDatabase.py
vb2py/PythonCard/font.py
vb2py/PythonCard/gadflyDatabase.py
vb2py/PythonCard/graphic.py
vb2py/PythonCard/helpful.py
vb2py/PythonCard/install-pythoncard.py
vb2py/PythonCard/log.py
vb2py/PythonCard/menu.py
vb2py/PythonCard/model.py
vb2py/PythonCard/pycrustrc.py
vb2py/PythonCard/registry.py
vb2py/PythonCard/resource.py
vb2py/PythonCard/setup.py
vb2py/PythonCard/simpleSizer.py
vb2py/PythonCard/singleton.py
vb2py/PythonCard/sound.py
vb2py/PythonCard/spec.py
vb2py/PythonCard/statusbar.py
vb2py/PythonCard/testIgnore.py
vb2py/PythonCard/timer.py
vb2py/PythonCard/turtle.py
vb2py/PythonCard/twistedModel.py
vb2py/PythonCard/util.py
vb2py/PythonCard/widget.py
vb2py/PythonCard/components/__init__.py
vb2py/PythonCard/components/bitmapcanvas.py
vb2py/PythonCard/components/button.py
vb2py/PythonCard/components/calendar.py
vb2py/PythonCard/components/checkbox.py
vb2py/PythonCard/components/choice.py
vb2py/PythonCard/components/codeeditor.py
vb2py/PythonCard/components/combobox.py
vb2py/PythonCard/components/container.py
vb2py/PythonCard/components/floatcanvas.py
vb2py/PythonCard/components/gauge.py
vb2py/PythonCard/components/grid.py
vb2py/PythonCard/components/htmlwindow.py
vb2Py-0.4.1.dist-info/LICENCE
vb2Py-0.4.1.dist-info/METADATA
vb2Py-0.4.1.dist-info/WHEEL
vb2Py-0.4.1.dist-info/top_level.txt
vb2Py-0.4.1.dist-info/RECORD
